odoo8_addon_project_stage_state_issue-8.0.1.0.0.99.dev14-py2.7-nspkg.pth
odoo8_addon_project_stage_state_issue-8.0.1.0.0.99.dev14.dist-info/METADATA
odoo8_addon_project_stage_state_issue-8.0.1.0.0.99.dev14.dist-info/RECORD
odoo8_addon_project_stage_state_issue-8.0.1.0.0.99.dev14.dist-info/WHEEL
odoo8_addon_project_stage_state_issue-8.0.1.0.0.99.dev14.dist-info/namespace_packages.txt
odoo8_addon_project_stage_state_issue-8.0.1.0.0.99.dev14.dist-info/top_level.txt
odoo_addons/project_stage_state_issue/README.md
odoo_addons/project_stage_state_issue/__init__.py
odoo_addons/project_stage_state_issue/__openerp__.py
odoo_addons/project_stage_state_issue/project_issue_model.py
odoo_addons/project_stage_state_issue/project_issue_view.xml
odoo_addons/project_stage_state_issue/i18n/ca.po
odoo_addons/project_stage_state_issue/i18n/cs.po
odoo_addons/project_stage_state_issue/i18n/da.po
odoo_addons/project_stage_state_issue/i18n/de.po
odoo_addons/project_stage_state_issue/i18n/es.po
odoo_addons/project_stage_state_issue/i18n/es_ES.po
odoo_addons/project_stage_state_issue/i18n/es_MX.po
odoo_addons/project_stage_state_issue/i18n/es_VE.po
odoo_addons/project_stage_state_issue/i18n/fi.po
odoo_addons/project_stage_state_issue/i18n/fr.po
odoo_addons/project_stage_state_issue/i18n/fr_CH.po
odoo_addons/project_stage_state_issue/i18n/gl.po
odoo_addons/project_stage_state_issue/i18n/hr.po
odoo_addons/project_stage_state_issue/i18n/hr_HR.po
odoo_addons/project_stage_state_issue/i18n/hu.po
odoo_addons/project_stage_state_issue/i18n/id.po
odoo_addons/project_stage_state_issue/i18n/it.po
odoo_addons/project_stage_state_issue/i18n/nb.po
odoo_addons/project_stage_state_issue/i18n/nb_NO.po
odoo_addons/project_stage_state_issue/i18n/nl.po
odoo_addons/project_stage_state_issue/i18n/nl_NL.po
odoo_addons/project_stage_state_issue/i18n/pl.po
odoo_addons/project_stage_state_issue/i18n/project_stage_state_issue.pot
odoo_addons/project_stage_state_issue/i18n/pt.po
odoo_addons/project_stage_state_issue/i18n/pt_BR.po
odoo_addons/project_stage_state_issue/i18n/pt_PT.po
odoo_addons/project_stage_state_issue/i18n/ro.po
odoo_addons/project_stage_state_issue/i18n/sk.po
odoo_addons/project_stage_state_issue/i18n/sl.po
odoo_addons/project_stage_state_issue/i18n/sv.po
odoo_addons/project_stage_state_issue/i18n/tr.po
